derivation/__init__.py
derivation/common.py
derivation/constraint.py
derivation/derivative.py
derivation/errors.py
derivation/federation.py
derivation-0.6.0.dist-info/WHEEL
derivation-0.6.0.dist-info/METADATA
derivation-0.6.0.dist-info/RECORD
