Metadata-Version: 2.1
Name: derivation
Version: 0.6.0
Summary: 
Author: Rain Wu
Author-email: rain.wu@appier.com
Requires-Python: >=3.9,<4.0
Classifier: Programming Language :: Python :: 3
Classifier: Programming Language :: Python :: 3.9
Classifier: Programming Language :: Python :: 3.10
Classifier: Programming Language :: Python :: 3.11
